wafec_tests_openstack_stub-1.0.2-py3.8-nspkg.pth
wafec_tests_openstack_stub/_auto.py
wafec_tests_openstack_stub/_base.py
wafec_tests_openstack_stub/_common.py
wafec_tests_openstack_stub/_configuration.py
wafec_tests_openstack_stub/_configuration_tests.py
wafec_tests_openstack_stub/_default_proxy_iterator.py
wafec_tests_openstack_stub/default_proxy.py
wafec_tests_openstack_stub/default_proxy_tests.py
wafec_tests_openstack_stub/exceptions.py
wafec_tests_openstack_stub/interception.py
wafec_tests_openstack_stub/interception_tests.py
wafec_tests_openstack_stub/main.py
wafec_tests_openstack_stub/utility.py
wafec_tests_openstack_stub-1.0.2.dist-info/METADATA
wafec_tests_openstack_stub-1.0.2.dist-info/WHEEL
wafec_tests_openstack_stub-1.0.2.dist-info/entry_points.txt
wafec_tests_openstack_stub-1.0.2.dist-info/namespace_packages.txt
wafec_tests_openstack_stub-1.0.2.dist-info/top_level.txt
wafec_tests_openstack_stub-1.0.2.dist-info/RECORD
